Metadata-Version: 2.1
Name: basenet
Version: 0.1.0
Summary: pytorch training tools
Home-page: UNKNOWN
Author: Ben Johnson
Author-email: bkj.322@gmail.com
License: Apache-2.0
Keywords: basenet,pytorch,training
Platform: UNKNOWN
